README.md
setup.cfg
setup.py
BootcampDSC/BootcampDSC.py
BootcampDSC/__init__.py
BootcampDSC.egg-info/PKG-INFO
BootcampDSC.egg-info/SOURCES.txt
BootcampDSC.egg-info/dependency_links.txt
BootcampDSC.egg-info/not-zip-safe
BootcampDSC.egg-info/top_level.txt