Metadata-Version: 2.1
Name: BootcampDSC
Version: 2.1.1
Summary: Data Literate Bootcamp DSC UMM
Home-page: UNKNOWN
Author: shandytp
Author-email: shandytsalasa@gmail.com
License: UNKNOWN
Platform: UNKNOWN
